mdanchors/__init__.py
mdanchors/converters.py
tests/__init__.py
tests/test_converters.py
md_anchors-0.2.2.dist-info/LICENSE
md_anchors-0.2.2.dist-info/METADATA
md_anchors-0.2.2.dist-info/WHEEL
md_anchors-0.2.2.dist-info/top_level.txt
md_anchors-0.2.2.dist-info/RECORD
