Metadata-Version: 2.1
Name: md-anchors
Version: 0.2.2
Summary: Tiny lib to work with Markdown / CommonMark anchors.
Home-page: https://github.com/LeMinaw/md-anchors
Author: LeMinaw
Author-email: leminaw@gmail.com
Classifier: Programming Language :: Python :: 3
Classifier: License :: OSI Approved :: MIT License
Classifier: Operating System :: OS Independent
Requires-Python: >=3.6
License-File: LICENSE
